re_patterns/__about__.py
re_patterns/__init__.py
re_patterns-1.1.0.dist-info/METADATA
re_patterns-1.1.0.dist-info/WHEEL
re_patterns-1.1.0.dist-info/licenses/LICENSE
re_patterns-1.1.0.dist-info/RECORD
