Metadata-Version: 2.1
Name: re-patterns
Version: 1.1.0
Summary: python regular expressions for humans
Project-URL: Homepage, https://github.com/Nagidal/re_patterns
Author-email: Sven Siegmund <sven.siegmund@gmail.com>
Keywords: expressions,re,regex,regular
Classifier: Development Status :: 5 - Production/Stable
Classifier: Environment :: Console
Classifier: Intended Audience :: Developers
Classifier: Intended Audience :: End Users/Desktop
Classifier: Intended Audience :: System Administrators
Classifier: License :: OSI Approved :: MIT License
Classifier: Natural Language :: English
Classifier: Operating System :: MacOS :: MacOS X
Classifier: Operating System :: Microsoft :: Windows
Classifier: Operating System :: OS Independent
Classifier: Operating System :: POSIX :: Linux
Classifier: Programming Language :: Python :: 3.9
Classifier: Topic :: Software Development
Requires-Python: >=3.9
